README.md
setup.cfg
setup.py
scratchplus/Cloud.py
scratchplus/Comments.py
scratchplus/Exceptions.py
scratchplus/Forum.py
scratchplus/Project.py
scratchplus/Session.py
scratchplus/Studios.py
scratchplus/UserProfiles.py
scratchplus/Users.py
scratchplus/__init__.py
scratchplus.egg-info/PKG-INFO
scratchplus.egg-info/SOURCES.txt
scratchplus.egg-info/dependency_links.txt
scratchplus.egg-info/not-zip-safe
scratchplus.egg-info/requires.txt
scratchplus.egg-info/top_level.txt