Metadata-Version: 2.1
Name: scratchplus
Version: 1.6.0
Summary: API wrapper for scratch
Home-page: https://github.com/noverd/ScratchPlus
Author: Gagarinten(Noverdo)
Author-email: thefinalspacestudio@gmail.com
License: UNKNOWN
Platform: UNKNOWN
